diced/__init__.py
diced_client-0.1.0.dist-info/METADATA
diced_client-0.1.0.dist-info/WHEEL
diced_client-0.1.0.dist-info/top_level.txt
diced_client-0.1.0.dist-info/RECORD
