Metadata-Version: 2.1
Name: diced-client
Version: 0.1.0
Summary: UNKNOWN
Home-page: UNKNOWN
License: UNKNOWN
Platform: UNKNOWN
Requires-Dist: httpx (==1.6.9)
Requires-Dist: pydantic (==2.5.2)
